secure_mcp_gateway/__init__.py
secure_mcp_gateway/api_models.py
secure_mcp_gateway/api_routes.py
secure_mcp_gateway/api_server.py
secure_mcp_gateway/cli.py
secure_mcp_gateway/client.py
secure_mcp_gateway/consts.py
secure_mcp_gateway/dependencies.py
secure_mcp_gateway/error_handling.py
secure_mcp_gateway/example_enkrypt_mcp_config.json
secure_mcp_gateway/exceptions.py
secure_mcp_gateway/gateway.py
secure_mcp_gateway/openapi.json
secure_mcp_gateway/utils.py
secure_mcp_gateway/version.py
secure_mcp_gateway/bad_mcps/__init__.py
secure_mcp_gateway/bad_mcps/bad_mcp.py
secure_mcp_gateway/bad_mcps/bad_output_mcp.py
secure_mcp_gateway/bad_mcps/command_injection_mcp.py
secure_mcp_gateway/bad_mcps/credential_theft_mcp.py
secure_mcp_gateway/bad_mcps/echo_mcp.py
secure_mcp_gateway/bad_mcps/echo_oauth_mcp.py
secure_mcp_gateway/bad_mcps/mpma_mcp.py
secure_mcp_gateway/bad_mcps/path_traversal_mcp.py
secure_mcp_gateway/bad_mcps/prompt_injection_mcp.py
secure_mcp_gateway/bad_mcps/rce_mcp.py
secure_mcp_gateway/bad_mcps/resource_exhaustion_mcp.py
secure_mcp_gateway/bad_mcps/schema_poisoning_mcp.py
secure_mcp_gateway/bad_mcps/session_management_mcp.py
secure_mcp_gateway/bad_mcps/ssrf_mcp.py
secure_mcp_gateway/bad_mcps/tool_poisoning_mcp.py
secure_mcp_gateway/bad_mcps/unauthenticated_access_mcp.py
secure_mcp_gateway/plugins/plugin_loader.py
secure_mcp_gateway/plugins/provider_loader.py
secure_mcp_gateway/plugins/auth/__init__.py
secure_mcp_gateway/plugins/auth/base.py
secure_mcp_gateway/plugins/auth/config_manager.py
secure_mcp_gateway/plugins/auth/enkrypt_provider.py
secure_mcp_gateway/plugins/auth/example_providers.py
secure_mcp_gateway/plugins/auth/local_apikey_provider.py
secure_mcp_gateway/plugins/guardrails/__init__.py
secure_mcp_gateway/plugins/guardrails/base.py
secure_mcp_gateway/plugins/guardrails/config_manager.py
secure_mcp_gateway/plugins/guardrails/enkrypt_provider.py
secure_mcp_gateway/plugins/guardrails/example_providers.py
secure_mcp_gateway/plugins/telemetry/__init__.py
secure_mcp_gateway-2.1.5.dist-info/licenses/LICENSE.txt
secure_mcp_gateway-2.1.5.dist-info/METADATA
secure_mcp_gateway-2.1.5.dist-info/WHEEL
secure_mcp_gateway-2.1.5.dist-info/entry_points.txt
secure_mcp_gateway-2.1.5.dist-info/top_level.txt
secure_mcp_gateway-2.1.5.dist-info/RECORD
