Metadata-Version: 2.4
Name: secure-mcp-gateway
Version: 2.1.5
Summary: Enkrypt Secure MCP Gateway
Home-page: https://github.com/enkryptai/secure-mcp-gateway
Author: Enkrypt AI Team
Author-email: Enkrypt AI Team <support@enkryptai.com>
License-Expression: MIT
Project-URL: Homepage, https://github.com/enkryptai/secure-mcp-gateway
Keywords: MCP,gateway,secure,middleware,async,python,model context protocol,guardrails,Enkrypt,Enkrypt AI,EnkryptAI,AI
Classifier: Development Status :: 4 - Beta
Classifier: Intended Audience :: Developers
Classifier: Programming Language :: Python :: 3
Classifier: Programming Language :: Python :: 3.8
Classifier: Programming Language :: Python :: 3.9
Classifier: Programming Language :: Python :: 3.10
Classifier: Programming Language :: Python :: 3.11
Classifier: Operating System :: OS Independent
Requires-Python: >=3.8
License-File: LICENSE.txt
Requires-Dist: flask~=3.1.2
Requires-Dist: flask-cors~=6.0.1
Requires-Dist: redis~=6.4.0
Requires-Dist: requests~=2.32.5
Requires-Dist: aiohttp~=3.12.15
Requires-Dist: fastapi~=0.115.6
Requires-Dist: uvicorn[standard]~=0.32.1
Requires-Dist: pydantic~=2.11.0
Requires-Dist: pydantic[email]~=2.11.0
Requires-Dist: email-validator~=2.2.0
Requires-Dist: python-json-logger~=3.3.0
Requires-Dist: python-dateutil~=2.9.0.post0
Requires-Dist: psutil~=6.1.0
Requires-Dist: cryptography~=45.0.7
Requires-Dist: pyjwt~=2.10.1
Requires-Dist: asyncio~=4.0.0
Requires-Dist: mcp[cli]~=1.13.1
Requires-Dist: opentelemetry-sdk~=1.36.0
Requires-Dist: opentelemetry-exporter-otlp~=1.36.0
Requires-Dist: opentelemetry-exporter-prometheus~=0.57b0
Requires-Dist: opentelemetry-instrumentation~=0.57b0
Requires-Dist: opentelemetry-instrumentation-requests~=0.57b0
Requires-Dist: structlog~=25.4.0
Dynamic: author
Dynamic: home-page
Dynamic: license-file
Dynamic: requires-dist
Dynamic: requires-python
